sqlmodel_yaml/__init__.py
sqlmodel_yaml/model.py
sqlmodel_yaml/yaml_loader.py
sqlmodel_yaml/scripts/__init__.py
sqlmodel_yaml/scripts/build_and_publish.py
sqlmodel_yaml/scripts/bump_version.py
sqlmodel_yaml/scripts/do_github_release.py
sqlmodel_yaml/scripts/format_and_lint.py
sqlmodel_yaml/scripts/run_tests.py
sqlmodel_yaml/scripts/script_common.py
sqlmodel_yaml-0.3.5.dist-info/METADATA
sqlmodel_yaml-0.3.5.dist-info/WHEEL
sqlmodel_yaml-0.3.5.dist-info/entry_points.txt
sqlmodel_yaml-0.3.5.dist-info/top_level.txt
sqlmodel_yaml-0.3.5.dist-info/RECORD
